{
    "meetings": [
        {
            "date": {
                "day": "Понедельник",
                "date": "15.06.20",
                "time": "15:30"
            },
            "address": {
                "hospital": "СПБ ГБУЗ 'Городская поликлиника №25'",
                "street": "пр. Солидарности, д. 1, к. 1, лит. А"
            },
            "doctor": {
                "name": "Малушко Т. Н.",
                "departmenе": "Хирургия",
                "img": "doctorOne"
            },
            "id": 1
        },
        {
            "date": {
                "day": "Понедельник",
                "date": "15.06.20",
                "time": "18:30"
            },
            "address": {
                "hospital": "СПБ ГБУЗ 'Городская поликлиника №25'",
                "street": "пр. Солидарности, д. 1, к. 1, лит. А"
            },
            "doctor": {
                "name": "Харьков В. С.",
                "departmenе": "Терапевтическое отделение",
                "img": "doctorTwo"
            },
            "id": 2
        },
        {
            "date": {
                "day": "Вторник",
                "date": "30.06.20",
                "time": "12:10"
            },
            "address": {
                "hospital": "СПБ ГБУЗ 'Городская поликлиника №25'",
                "street": "пр. Солидарности, д. 1, к. 1, лит. А"
            },
            "doctor": {
                "name": "Малушко Т. Н.",
                "departmenе": "Хирургия",
                "img": "doctorOne"
            },
            "id": 3
        },
        {
            "date": {
                "day": "Четверг",
                "date": "02.07.30",
                "time": "12:30"
            },
            "address": {
                "hospital": "СПБ ГБУЗ 'Городская поликлиника №25'",
                "street": "пр. Солидарности, д. 1, к. 1, лит. А"
            },
            "doctor": {
                "name": "Харьков В. С.",
                "departmenе": "Терапевтическое отделение",
                "img": "doctorTwo"
            },
            "id": 4
        }
    ]
}
